tweetle/__init__.py
tweetle/cli.py
tweetle/packages/ProjPySQL.py
tweetle/packages/__init__.py
tweetle/packages/commands.py
tweetle/packages/tweefeed.py
tweetle-1.0.1.dist-info/LICENSE
tweetle-1.0.1.dist-info/METADATA
tweetle-1.0.1.dist-info/WHEEL
tweetle-1.0.1.dist-info/entry_points.txt
tweetle-1.0.1.dist-info/top_level.txt
tweetle-1.0.1.dist-info/RECORD
