Metadata-Version: 2.1
Name: tweetle
Version: 1.0.1
Summary: A CLI made to control your twitter account and get analytical data
Home-page: https://github.com/4RCAN3/Tweetle
Author: ARC4N3
Author-email: arcaneisc00l@gmail.com
License: MIT
Platform: UNKNOWN
Classifier: Programming Language :: Python :: 3
Classifier: License :: OSI Approved :: MIT License
Classifier: Operating System :: OS Independent
Requires-Dist: art (==5.1)
Requires-Dist: ascii-graph (==1.5.1)
Requires-Dist: ascii-magic (==1.5.5)
Requires-Dist: certifi (==2020.12.5)
Requires-Dist: chardet (==4.0.0)
Requires-Dist: click (==7.1.2)
Requires-Dist: colorama (==0.4.4)
Requires-Dist: idna (==2.10)
Requires-Dist: mysql-connector-python (==8.0.23)
Requires-Dist: oauthlib (==3.1.0)
Requires-Dist: Pillow (==8.2.0)
Requires-Dist: prettytable (==2.1.0)
Requires-Dist: protobuf (==3.15.8)
Requires-Dist: PySocks (==1.7.1)
Requires-Dist: python-dotenv (==0.17.0)
Requires-Dist: requests (==2.25.1)
Requires-Dist: requests-oauthlib (==1.3.0)
Requires-Dist: six (==1.15.0)
Requires-Dist: stdiomask (==0.0.6)
Requires-Dist: tweepy (==3.10.0)
Requires-Dist: urllib3 (==1.26.4)
Requires-Dist: wcwidth (==0.2.5)
